iot_api_client/__init__.py
iot_api_client/api_client.py
iot_api_client/configuration.py
iot_api_client/exceptions.py
iot_api_client/rest.py
iot_api_client/schemas.py
iot_api_client/apis/__init__.py
iot_api_client/apis/path_to_api.py
iot_api_client/apis/tag_to_api.py
iot_api_client/apis/paths/__init__.py
iot_api_client/apis/paths/v1_lora_devices_.py
iot_api_client/apis/paths/v1_lora_freq_plans_.py
iot_api_client/apis/paths/v2_dashboards.py
iot_api_client/apis/paths/v2_dashboards_id.py
iot_api_client/apis/paths/v2_dashboards_id_clone.py
iot_api_client/apis/paths/v2_dashboards_id_share_request.py
iot_api_client/apis/paths/v2_dashboards_id_shares.py
iot_api_client/apis/paths/v2_dashboards_id_shares_user_id.py
iot_api_client/apis/paths/v2_dashboards_id_template.py
iot_api_client/apis/paths/v2_dashboards_id_widgets_widget_id_variables.py
iot_api_client/apis/paths/v2_devices.py
iot_api_client/apis/paths/v2_devices_id.py
iot_api_client/apis/paths/v2_devices_id_certs.py
iot_api_client/apis/paths/v2_devices_id_certs_cid.py
iot_api_client/apis/paths/v2_devices_id_events.py
iot_api_client/apis/paths/v2_devices_id_ota.py
iot_api_client/apis/paths/v2_devices_id_pass.py
iot_api_client/apis/paths/v2_devices_id_properties.py
iot_api_client/apis/paths/v2_devices_id_properties_pid.py
iot_api_client/apis/paths/v2_devices_id_status.py
iot_api_client/apis/paths/v2_devices_id_tags.py
iot_api_client/apis/paths/v2_devices_id_tags_key.py
iot_api_client/apis/paths/v2_series_batch_query.py
iot_api_client/apis/paths/v2_series_batch_query_raw.py
iot_api_client/apis/paths/v2_series_batch_query_raw_lastvalue.py
iot_api_client/apis/paths/v2_series_historic_data.py
iot_api_client/apis/paths/v2_things.py
iot_api_client/apis/paths/v2_things_id.py
iot_api_client/apis/paths/v2_things_id_clone.py
iot_api_client/apis/paths/v2_things_id_properties.py
iot_api_client/apis/paths/v2_things_id_properties_pid.py
iot_api_client/apis/paths/v2_things_id_properties_pid_publish.py
arduino_iot_client-2.0.1.dist-info/LICENSE
arduino_iot_client-2.0.1.dist-info/METADATA
arduino_iot_client-2.0.1.dist-info/WHEEL
arduino_iot_client-2.0.1.dist-info/top_level.txt
arduino_iot_client-2.0.1.dist-info/RECORD
