Metadata-Version: 2.1
Name: arduino-iot-client
Version: 2.0.1
Summary: Iot API
Home-page: 
Author-email: 
Keywords: OpenAPI,OpenAPI-Generator,Iot API
License-File: LICENSE
Requires-Dist: urllib3 >=1.15
Requires-Dist: six >=1.10
Requires-Dist: certifi
Requires-Dist: python-dateutil
